django_analyses/__init__.py
django_analyses/admin.py
django_analyses/apps.py
django_analyses/pipeline_runner.py
django_analyses/urls.py
django_analyses/filters/__init__.py
django_analyses/filters/analysis.py
django_analyses/filters/category.py
django_analyses/filters/input/__init__.py
django_analyses/filters/input/input.py
django_analyses/filters/input/input_definition.py
django_analyses/filters/output/__init__.py
django_analyses/filters/output/output.py
django_analyses/filters/output/output_definition.py
django_analyses/filters/pipeline/__init__.py
django_analyses/filters/pipeline/node.py
django_analyses/filters/pipeline/pipe.py
django_analyses/filters/pipeline/pipeline.py
django_analyses/migrations/0001_initial.py
django_analyses/migrations/__init__.py
django_analyses/models/__init__.py
django_analyses/models/analysis.py
django_analyses/models/analysis_version.py
django_analyses/models/category.py
django_analyses/models/run.py
django_analyses/models/input/__init__.py
django_analyses/models/input/input.py
django_analyses/models/input/input_specification.py
django_analyses/models/input/utils.py
django_analyses/models/input/definitions/__init__.py
django_analyses/models/input/definitions/boolean_input_definition.py
django_analyses/models/input/definitions/directory_input_definition.py
django_analyses/models/input/definitions/file_input_definition.py
django_analyses/models/input/definitions/float_input_definition.py
django_analyses/models/input/definitions/input_definition.py
django_analyses/models/input/definitions/input_definitions.py
django_analyses/models/input/definitions/integer_input_definition.py
django_analyses/models/input/definitions/list_input_definition.py
django_analyses/models/input/definitions/messages.py
django_analyses/models/input/definitions/number_input_definition.py
django_analyses/models/input/definitions/string_input_definition.py
django_analyses/models/input/types/__init__.py
django_analyses/models/input/types/boolean_input.py
django_analyses-0.1.0.dist-info/LICENSE
django_analyses-0.1.0.dist-info/METADATA
django_analyses-0.1.0.dist-info/WHEEL
django_analyses-0.1.0.dist-info/top_level.txt
django_analyses-0.1.0.dist-info/RECORD
